{"air_date":"2018-03-19","crew":[{"id":1382168,"credit_id":"56f41101925141769e001e90","name":"Alex Katsnelson","department":"Writing","job":"Writer","gender":0,"profile_path":null},{"id":1579755,"credit_id":"5724ebc39251411d090002b0","name":"Mike Costa","department":"Writing","job":"Writer","gender":0,"profile_path":null},{"id":139247,"credit_id":"5ada436dc3a368690f0006de","name":"Hanelle M. Culpepper","department":"Directing","job":"Director","gender":1,"profile_path":"/wffoNcm5zKRyhERxZO0osWOZX6t.jpg"}],"episode_number":18,"guest_stars":[{"id":1233749,"name":"Fiona Gubelmann","credit_id":"5ab593be0e0a261fee0010b5","character":"Kay/Maddie","order":106,"gender":1,"profile_path":"/c80VyX8RyupJXb7EqTxHNHtN4Cn.jpg"},{"id":171827,"name":"Joshua Gomez","credit_id":"5ab593de9251413964000f99","character":"Neil Berger","order":107,"gender":2,"profile_path":"/5dJQgb32xHN8KH0Pxolw5bxGjGW.jpg"},{"id":173964,"name":"Andrew Leeds","credit_id":"5ab5940b9251413964000fb4","character":"Joel","order":108,"gender":2,"profile_path":"/w9aIFV2E4qIA19wEaarPR3Dxtbu.jpg"},{"id":54503,"name":"Adam G. Sevani","credit_id":"5ad37b2fc3a3683ef102c1b3","character":"Brandon","order":115,"gender":2,"profile_path":"/2GQdyHQG4aw0FOokajOr7Wvhpyl.jpg"},{"id":1590308,"name":"Susan Berger","credit_id":"5b23a1fdc3a36831db0053f4","character":"Olga","order":139,"gender":1,"profile_path":"/yOiQkLTJ1pRV8rFs7Od8nl0wOOj.jpg"},{"id":1472602,"name":"Sandra Lee Gimpel","credit_id":"5b2a39cc92514138fb004308","character":"Elderly Woman","order":140,"gender":1,"profile_path":"/1WqouqgOnP1MXdVc53KC7TBncID.jpg"},{"id":2651389,"name":"Christopher Ashman","credit_id":"5ec9f18b6c84920020310e7b","character":"Ray Dwight","order":524,"gender":2,"profile_path":"/1UHRc4JdsI53gCzTkLF3XfX5rk1.jpg"},{"id":60258,"name":"Mark DeCarlo","credit_id":"5ec9f8d7140bad001b1be11e","character":"Chance","order":525,"gender":2,"profile_path":"/9KK4v1CaHdpn0vTukzOgirRPR7j.jpg"},{"id":2651407,"name":"Jessica Trainham","credit_id":"5ec9f9a4140bad45ee15aa7c","character":"Alice","order":526,"gender":1,"profile_path":"/zcDRMmAY7Opd7ORnhpP7XvgJ2GL.jpg"},{"id":1810666,"name":"M.Q. Tran","credit_id":"5ec9fa90eb79c2001ea3740f","character":"Barista","order":527,"gender":0,"profile_path":"/8ZeWBt1zMM4eLUAFpE7vauIXKV.jpg"},{"id":1116717,"name":"Amy Tsang","credit_id":"5ec9fc2e0fb17f001c7c7db8","character":"Emma Matthews","order":528,"gender":1,"profile_path":"/kGXqCHSbDmOiwINDDoxHEof3ZgQ.jpg"}],"name":"Último coração partido","overview":"Chloe e Lúcifer investigam um assassino que ataca casais apaixonados. Pierce suspeita que o caso possa estar relacionado ao seu passado.","id":1445258,"production_code":"","season_number":3,"still_path":"/nNKFX4ffK5mUBkAvRbHvElFx82e.jpg","vote_average":7.818,"vote_count":11}