{"cast":[{"character":"Walter White","credit_id":"52542282760ee313280017f9","gender":2,"id":17419,"name":"Bryan Cranston","order":0,"profile_path":"/7Jahy5LZX2Fo8fGJltMreAI49hC.jpg"},{"character":"Skyler White","credit_id":"52542282760ee3132800181b","gender":1,"id":134531,"name":"Anna Gunn","order":2,"profile_path":"/adppyeu1a4REN3khtgmXusrapFi.jpg"},{"character":"Jesse Pinkman","credit_id":"52542282760ee31328001845","gender":2,"id":84497,"name":"Aaron Paul","order":1,"profile_path":"/u8UdsB9yenM4uHEjmce4nkBn48X.jpg"},{"character":"Hank Schrader","credit_id":"52542283760ee3132800187b","gender":2,"id":14329,"name":"Dean Norris","order":3,"profile_path":"/fXbHgZxCEclcTxV8MpeBXhe2OJS.jpg"},{"character":"Marie Schrader","credit_id":"52542283760ee31328001891","gender":1,"id":1217934,"name":"Betsy Brandt","order":4,"profile_path":"/zmhhPmXnwjSzVyoTVL93i1EkLRK.jpg"},{"character":"Walter White Jr.","credit_id":"52542284760ee313280018a9","gender":2,"id":209674,"name":"RJ Mitte","order":5,"profile_path":"/aG6NYV2EgzBFLRIl7vvbtd7go1j.jpg"}],"crew":[{"id":1223198,"credit_id":"52542287760ee31328001ad1","name":"Moira Walley-Beckett","department":"Writing","job":"Writer","gender":1,"profile_path":"/nysIQz4lEMqar1Bd3gBaCzuwSde.jpg"},{"id":1214445,"credit_id":"52542280760ee313280013a6","name":"Phil Abraham","department":"Directing","job":"Director","gender":2,"profile_path":null}],"guest_stars":[{"id":78080,"name":"Krysten Ritter","credit_id":"5254227e760ee31328001037","character":"Jane Margolis","order":2,"gender":1,"profile_path":"/bII7CIrRAc7JdDSfG8oDIbRPQCx.jpg"},{"id":111014,"name":"Carl Savering","credit_id":"52754154760ee335780056e8","character":"Bob","order":71,"gender":0,"profile_path":null},{"id":11077,"name":"John de Lancie","credit_id":"52542280760ee31328001390","character":"Donald Margolis","order":73,"gender":2,"profile_path":"/e9GsjWaW9fabT22ceLzesJhUgzd.jpg"},{"id":20379,"name":"Christopher Cousins","credit_id":"527504f6760ee347c912980c","character":"Ted Beneke","order":136,"gender":2,"profile_path":"/9fmoeZLGbJfiYU6mIbrUkjF9wsR.jpg"},{"id":61535,"name":"Steven Michael Quezada","credit_id":"5271b489760ee35b3e0881a7","character":"Steven Gomez","order":173,"gender":2,"profile_path":"/4BRo6oc26kePVYxgNzYwUrDagVO.jpg"},{"id":115688,"name":"Carmen Serano","credit_id":"52542273760ee31328000676","character":"Carmen Molina","order":176,"gender":1,"profile_path":"/nzJEe2UqvvMIBJZP1aeFEj4EunN.jpg"}],"id":62101}