{
  "air_date": "2016-10-31",
  "crew": [
    {
      "id": 205641,
      "credit_id": "56ff97a09251416783001aa1",
      "name": "Eagle Egilsson",
      "department": "Directing",
      "job": "Director",
      "gender": 2,
      "profile_path": null
    },
    {
      "id": 1490537,
      "credit_id": "5700432ec3a3686e9200370c",
      "name": "Chris Rafferty",
      "department": "Writing",
      "job": "Writer",
      "gender": 0,
      "profile_path": null
    }
  ],
  "episode_number": 6,
  "guest_stars": [
    {
      "id": 1710661,
      "name": "Liam Hall",
      "credit_id": "5991923e92514143ad00ea22",
      "character": "Edgar Romero",
      "order": 81,
      "gender": 2,
      "profile_path": "/wyt24ecMpaBpCuSYVi5IIf5e24D.jpg"
    },
    {
      "id": 943154,
      "name": "Joshua Bitton",
      "credit_id": "5ec831ceae2811001f3e230f",
      "character": "Wes Williams",
      "order": 281,
      "gender": 2,
      "profile_path": "/d5N7kvWXwmQctqmVNvdOB6UxYsK.jpg"
    },
    {
      "id": 1449094,
      "name": "Amad Jackson",
      "credit_id": "5ec832796c8492001f2a65be",
      "character": "Freddy Loomis",
      "order": 282,
      "gender": 2,
      "profile_path": "/ij3FpXfmLym50f5kPZl5Pr1Wlhu.jpg"
    },
    {
      "id": 175234,
      "name": "Nicole LaPlaca",
      "credit_id": "5ec83384140bad001d1ba764",
      "character": "Shauna",
      "order": 283,
      "gender": 1,
      "profile_path": "/wgH9GTUASKZGnpYjeg4pxFmH9RV.jpg"
    },
    {
      "id": 1884548,
      "name": "Joel Cottingham",
      "credit_id": "5ec8350cae281100203bcae6",
      "character": "Zombie Priest",
      "order": 284,
      "gender": 2,
      "profile_path": "/jwYrNTzcVEsulpH4mbOkpmZxgiz.jpg"
    },
    {
      "id": 236839,
      "name": "AnnaMaria Demara",
      "credit_id": "5ec836579979d2001f35e1d9",
      "character": "Peggy Russo",
      "order": 285,
      "gender": 1,
      "profile_path": "/6uwR4zJMDSC1W4Gr0hCn5rsv6xJ.jpg"
    },
    {
      "id": 2458601,
      "name": "Tina Georgieva",
      "credit_id": "5ec836b0d2147c0021b70c90",
      "character": "Club Goer",
      "order": 286,
      "gender": 1,
      "profile_path": "/vtyOaQwez0mJ2CGlBjhTFmlrNJZ.jpg"
    },
    {
      "id": 80405,
      "name": "Karen Holness",
      "credit_id": "5ec837a9595a56001cb94e1e",
      "character": "Sidney Loomis",
      "order": 287,
      "gender": 1,
      "profile_path": "/mKyNgWJMLA3dKRNHyAU0qaZWSRY.jpg"
    },
    {
      "id": 2649581,
      "name": "Sean Hunter",
      "credit_id": "5ec837cfa3d027002178b414",
      "character": "Jason Myers",
      "order": 288,
      "gender": 2,
      "profile_path": "/tE3mfEXbnZbeBvN0YP7B5T75Ugu.jpg"
    },
    {
      "id": 1487353,
      "name": "Victoria Ortiz",
      "credit_id": "5ec83b649979d2001f35e612",
      "character": "Teenage Employee",
      "order": 289,
      "gender": 3,
      "profile_path": "/2uzdj4Ni4TF6nIalBhjfanoeD5c.jpg"
    },
    {
      "id": 1476335,
      "name": "David Pérez",
      "credit_id": "5ec83c2de635710022d03eac",
      "character": "Neighbor",
      "order": 290,
      "gender": 0,
      "profile_path": "/wwD3mUVTxeO1iozfmO1Xs8kamBG.jpg"
    }
  ],
  "name": "Eu sou um monstro",
  "overview": "Um casamento com temática zumbi acaba em morte. Maze sai com Trixie no Dia das Bruxas. Lucifer tem uma conversa importante com a Dra. Linda.",
  "id": 1227225,
  "production_code": "T13.20056",
  "season_number": 2,
  "still_path": "/6DD0lTpO4KP8A8J6VBGamcym4i8.jpg",
  "vote_average": 7.947,
  "vote_count": 19
}